{
  "audio": "tests/fixtures/audio/arctic_slt_a0001.wav",
  "case": "intensity-defaults",
  "frames": [
    {
      "db": 41.901034,
      "time": 0.0335
    },
    {
      "db": 44.110388,
      "time": 0.0415
    },
    {
      "db": 46.636588,
      "time": 0.0495
    },
    {
      "db": 46.088719,
      "time": 0.0575
    },
    {
      "db": 44.017367,
      "time": 0.0655
    },
    {
      "db": 43.015031,
      "time": 0.0735
    },
    {
      "db": 41.838344,
      "time": 0.0815
    },
    {
      "db": 41.124689,
      "time": 0.0895
    },
    {
      "db": 40.189063,
      "time": 0.0975
    },
    {
      "db": 40.75024,
      "time": 0.1055
    },
    {
      "db": 40.518182,
      "time": 0.1135
    },
    {
      "db": 40.486937,
      "time": 0.1215
    },
    {
      "db": 40.548478,
      "time": 0.1295
    },
    {
      "db": 46.549197,
      "time": 0.1375
    },
    {
      "db": 50.996251,
      "time": 0.1455
    },
    {
      "db": 50.702274,
      "time": 0.1535
    },
    {
      "db": 46.048371,
      "time": 0.1615
    },
    {
      "db": 41.306183,
      "time": 0.1695
    },
    {
      "db": 41.082865,
      "time": 0.1775
    },
    {
      "db": 40.469356,
      "time": 0.1855
    },
    {
      "db": 46.218613,
      "time": 0.1935
    },
    {
      "db": 56.074848,
      "time": 0.2015
    },
    {
      "db": 62.515027,
      "time": 0.2095
    },
    {
      "db": 70.228429,
      "time": 0.2175
    },
    {
      "db": 76.274429,
      "time": 0.2255
    },
    {
      "db": 78.729579,
      "time": 0.2335
    },
    {
      "db": 79.309664,
      "time": 0.2415
    },
    {
      "db": 79.796029,
      "time": 0.2495
    },
    {
      "db": 80.263005,
      "time": 0.2575
    },
    {
      "db": 81.031796,
      "time": 0.2655
    },
    {
      "db": 82.07115,
      "time": 0.2735
    },
    {
      "db": 82.709837,
      "time": 0.2815
    },
    {
      "db": 82.777863,
      "time": 0.2895
    },
    {
      "db": 82.406776,
      "time": 0.2975
    },
    {
      "db": 81.757051,
      "time": 0.3055
    },
    {
      "db": 80.916474,
      "time": 0.3135
    },
    {
      "db": 79.884079,
      "time": 0.3215
    },
    {
      "db": 78.735756,
      "time": 0.3295
    },
    {
      "db": 77.838378,
      "time": 0.3375
    },
    {
      "db": 77.125619,
      "time": 0.3455
    },
    {
      "db": 75.848971,
      "time": 0.3535
    },
    {
      "db": 73.204238,
      "time": 0.3615
    },
    {
      "db": 68.246665,
      "time": 0.3695
    },
    {
      "db": 60.158305,
      "time": 0.3775
    },
    {
      "db": 51.68333,
      "time": 0.3855
    },
    {
      "db": 49.576496,
      "time": 0.3935
    },
    {
      "db": 49.006696,
      "time": 0.4015
    },
    {
      "db": 48.742578,
      "time": 0.4095
    },
    {
      "db": 49.122469,
      "time": 0.4175
    },
    {
      "db": 50.396026,
      "time": 0.4255
    },
    {
      "db": 52.651588,
      "time": 0.4335
    },
    {
      "db": 56.005978,
      "time": 0.4415
    },
    {
      "db": 66.988914,
      "time": 0.4495
    },
    {
      "db": 75.618903,
      "time": 0.4575
    },
    {
      "db": 79.891252,
      "time": 0.4655
    },
    {
      "db": 80.986654,
      "time": 0.4735
    },
    {
      "db": 80.585198,
      "time": 0.4815
    },
    {
      "db": 80.263912,
      "time": 0.4895
    },
    {
      "db": 80.272188,
      "time": 0.4975
    },
    {
      "db": 80.387876,
      "time": 0.5055
    },
    {
      "db": 80.50637,
      "time": 0.5135
    },
    {
      "db": 80.589008,
      "time": 0.5215
    },
    {
      "db": 80.652952,
      "time": 0.5295
    },
    {
      "db": 80.709214,
      "time": 0.5375
    },
    {
      "db": 80.741992,
      "time": 0.5455
    },
    {
      "db": 80.750479,
      "time": 0.5535
    },
    {
      "db": 80.747915,
      "time": 0.5615
    },
    {
      "db": 80.716949,
      "time": 0.5695
    },
    {
      "db": 80.667051,
      "time": 0.5775
    },
    {
      "db": 80.66214,
      "time": 0.5855
    },
    {
      "db": 80.719942,
      "time": 0.5935
    },
    {
      "db": 80.778107,
      "time": 0.6015
    },
    {
      "db": 80.873628,
      "time": 0.6095
    },
    {
      "db": 81.073915,
      "time": 0.6175
    },
    {
      "db": 81.320763,
      "time": 0.6255
    },
    {
      "db": 81.513082,
      "time": 0.6335
    },
    {
      "db": 81.544918,
      "time": 0.6415
    },
    {
      "db": 81.28937,
      "time": 0.6495
    },
    {
      "db": 80.663705,
      "time": 0.6575
    },
    {
      "db": 79.428441,
      "time": 0.6655
    },
    {
      "db": 77.252684,
      "time": 0.6735
    },
    {
      "db": 74.561932,
      "time": 0.6815
    },
    {
      "db": 72.4873,
      "time": 0.6895
    },
    {
      "db": 70.86881,
      "time": 0.6975
    },
    {
      "db": 69.220067,
      "time": 0.7055
    },
    {
      "db": 67.488688,
      "time": 0.7135
    },
    {
      "db": 65.404126,
      "time": 0.7215
    },
    {
      "db": 62.659179,
      "time": 0.7295
    },
    {
      "db": 59.287897,
      "time": 0.7375
    },
    {
      "db": 55.385572,
      "time": 0.7455
    },
    {
      "db": 51.874993,
      "time": 0.7535
    },
    {
      "db": 50.728887,
      "time": 0.7615
    },
    {
      "db": 49.892914,
      "time": 0.7695
    },
    {
      "db": 47.563042,
      "time": 0.7775
    },
    {
      "db": 48.539973,
      "time": 0.7855
    },
    {
      "db": 53.461184,
      "time": 0.7935
    },
    {
      "db": 58.87139,
      "time": 0.8015
    },
    {
      "db": 65.83839,
      "time": 0.8095
    },
    {
      "db": 71.26889,
      "time": 0.8175
    },
    {
      "db": 74.251125,
      "time": 0.8255
    },
    {
      "db": 75.803211,
      "time": 0.8335
    },
    {
      "db": 76.66698,
      "time": 0.8415
    },
    {
      "db": 76.51871,
      "time": 0.8495
    },
    {
      "db": 74.841213,
      "time": 0.8575
    },
    {
      "db": 72.065781,
      "time": 0.8655
    },
    {
      "db": 69.811072,
      "time": 0.8735
    },
    {
      "db": 68.178906,
      "time": 0.8815
    },
    {
      "db": 66.656933,
      "time": 0.8895
    },
    {
      "db": 65.051358,
      "time": 0.8975
    },
    {
      "db": 63.206401,
      "time": 0.9055
    },
    {
      "db": 63.053869,
      "time": 0.9135
    },
    {
      "db": 67.877301,
      "time": 0.9215
    },
    {
      "db": 73.356716,
      "time": 0.9295
    },
    {
      "db": 76.873647,
      "time": 0.9375
    },
    {
      "db": 78.310222,
      "time": 0.9455
    },
    {
      "db": 78.208073,
      "time": 0.9535
    },
    {
      "db": 77.580805,
      "time": 0.9615
    },
    {
      "db": 77.242152,
      "time": 0.9695
    },
    {
      "db": 77.194685,
      "time": 0.9775
    },
    {
      "db": 77.124605,
      "time": 0.9855
    },
    {
      "db": 76.903262,
      "time": 0.9935
    },
    {
      "db": 76.695982,
      "time": 1.0015
    },
    {
      "db": 76.671181,
      "time": 1.0095
    },
    {
      "db": 76.831415,
      "time": 1.0175
    },
    {
      "db": 77.129472,
      "time": 1.0255
    },
    {
      "db": 77.543168,
      "time": 1.0335
    },
    {
      "db": 78.06279,
      "time": 1.0415
    },
    {
      "db": 78.633285,
      "time": 1.0495
    },
    {
      "db": 79.386617,
      "time": 1.0575
    },
    {
      "db": 80.689397,
      "time": 1.0655
    },
    {
      "db": 81.802146,
      "time": 1.0735
    },
    {
      "db": 82.323928,
      "time": 1.0815
    },
    {
      "db": 82.593392,
      "time": 1.0895
    },
    {
      "db": 82.608558,
      "time": 1.0975
    },
    {
      "db": 82.069957,
      "time": 1.1055
    },
    {
      "db": 80.457191,
      "time": 1.1135
    },
    {
      "db": 77.216712,
      "time": 1.1215
    },
    {
      "db": 72.212148,
      "time": 1.1295
    },
    {
      "db": 67.691317,
      "time": 1.1375
    },
    {
      "db": 68.441404,
      "time": 1.1455
    },
    {
      "db": 72.863456,
      "time": 1.1535
    },
    {
      "db": 76.232887,
      "time": 1.1615
    },
    {
      "db": 77.617773,
      "time": 1.1695
    },
    {
      "db": 77.901434,
      "time": 1.1775
    },
    {
      "db": 77.872835,
      "time": 1.1855
    },
    {
      "db": 77.742539,
      "time": 1.1935
    },
    {
      "db": 77.491028,
      "time": 1.2015
    },
    {
      "db": 76.994852,
      "time": 1.2095
    },
    {
      "db": 75.964176,
      "time": 1.2175
    },
    {
      "db": 73.970072,
      "time": 1.2255
    },
    {
      "db": 70.569718,
      "time": 1.2335
    },
    {
      "db": 65.502264,
      "time": 1.2415
    },
    {
      "db": 59.752322,
      "time": 1.2495
    },
    {
      "db": 58.250515,
      "time": 1.2575
    },
    {
      "db": 60.410098,
      "time": 1.2655
    },
    {
      "db": 62.979575,
      "time": 1.2735
    },
    {
      "db": 64.98682,
      "time": 1.2815
    },
    {
      "db": 65.487285,
      "time": 1.2895
    },
    {
      "db": 64.7616,
      "time": 1.2975
    },
    {
      "db": 63.011868,
      "time": 1.3055
    },
    {
      "db": 60.536712,
      "time": 1.3135
    },
    {
      "db": 58.3718,
      "time": 1.3215
    },
    {
      "db": 56.431593,
      "time": 1.3295
    },
    {
      "db": 57.6659,
      "time": 1.3375
    },
    {
      "db": 66.076943,
      "time": 1.3455
    },
    {
      "db": 72.054038,
      "time": 1.3535
    },
    {
      "db": 74.759038,
      "time": 1.3615
    },
    {
      "db": 75.928954,
      "time": 1.3695
    },
    {
      "db": 76.727176,
      "time": 1.3775
    },
    {
      "db": 77.060965,
      "time": 1.3855
    },
    {
      "db": 76.918968,
      "time": 1.3935
    },
    {
      "db": 76.640168,
      "time": 1.4015
    },
    {
      "db": 76.491239,
      "time": 1.4095
    },
    {
      "db": 76.459783,
      "time": 1.4175
    },
    {
      "db": 76.497211,
      "time": 1.4255
    },
    {
      "db": 76.632217,
      "time": 1.4335
    },
    {
      "db": 76.823673,
      "time": 1.4415
    },
    {
      "db": 76.982285,
      "time": 1.4495
    },
    {
      "db": 77.090203,
      "time": 1.4575
    },
    {
      "db": 77.192363,
      "time": 1.4655
    },
    {
      "db": 77.31381,
      "time": 1.4735
    },
    {
      "db": 77.400379,
      "time": 1.4815
    },
    {
      "db": 77.388154,
      "time": 1.4895
    },
    {
      "db": 77.360756,
      "time": 1.4975
    },
    {
      "db": 77.383209,
      "time": 1.5055
    },
    {
      "db": 77.386263,
      "time": 1.5135
    },
    {
      "db": 77.332511,
      "time": 1.5215
    },
    {
      "db": 77.223748,
      "time": 1.5295
    },
    {
      "db": 77.076665,
      "time": 1.5375
    },
    {
      "db": 76.929847,
      "time": 1.5455
    },
    {
      "db": 76.776807,
      "time": 1.5535
    },
    {
      "db": 76.562249,
      "time": 1.5615
    },
    {
      "db": 76.216868,
      "time": 1.5695
    },
    {
      "db": 75.759703,
      "time": 1.5775
    },
    {
      "db": 75.240378,
      "time": 1.5855
    },
    {
      "db": 74.7204,
      "time": 1.5935
    },
    {
      "db": 74.236357,
      "time": 1.6015
    },
    {
      "db": 73.736248,
      "time": 1.6095
    },
    {
      "db": 73.156832,
      "time": 1.6175
    },
    {
      "db": 72.422838,
      "time": 1.6255
    },
    {
      "db": 71.532045,
      "time": 1.6335
    },
    {
      "db": 70.483144,
      "time": 1.6415
    },
    {
      "db": 68.973913,
      "time": 1.6495
    },
    {
      "db": 66.723261,
      "time": 1.6575
    },
    {
      "db": 63.749454,
      "time": 1.6655
    },
    {
      "db": 59.923542,
      "time": 1.6735
    },
    {
      "db": 55.068317,
      "time": 1.6815
    },
    {
      "db": 50.30373,
      "time": 1.6895
    },
    {
      "db": 47.896524,
      "time": 1.6975
    },
    {
      "db": 47.17785,
      "time": 1.7055
    },
    {
      "db": 46.829684,
      "time": 1.7135
    },
    {
      "db": 45.856523,
      "time": 1.7215
    },
    {
      "db": 44.330633,
      "time": 1.7295
    },
    {
      "db": 43.17892,
      "time": 1.7375
    },
    {
      "db": 42.894851,
      "time": 1.7455
    },
    {
      "db": 44.392744,
      "time": 1.7535
    },
    {
      "db": 45.941722,
      "time": 1.7615
    },
    {
      "db": 46.856025,
      "time": 1.7695
    },
    {
      "db": 49.406844,
      "time": 1.7775
    },
    {
      "db": 52.593633,
      "time": 1.7855
    },
    {
      "db": 53.887141,
      "time": 1.7935
    },
    {
      "db": 53.171236,
      "time": 1.8015
    },
    {
      "db": 52.783215,
      "time": 1.8095
    },
    {
      "db": 62.026316,
      "time": 1.8175
    },
    {
      "db": 71.225806,
      "time": 1.8255
    },
    {
      "db": 76.601585,
      "time": 1.8335
    },
    {
      "db": 79.377201,
      "time": 1.8415
    },
    {
      "db": 80.544345,
      "time": 1.8495
    },
    {
      "db": 80.700842,
      "time": 1.8575
    },
    {
      "db": 80.229626,
      "time": 1.8655
    },
    {
      "db": 79.365272,
      "time": 1.8735
    },
    {
      "db": 78.344837,
      "time": 1.8815
    },
    {
      "db": 77.458081,
      "time": 1.8895
    },
    {
      "db": 76.974499,
      "time": 1.8975
    },
    {
      "db": 77.005627,
      "time": 1.9055
    },
    {
      "db": 77.381339,
      "time": 1.9135
    },
    {
      "db": 77.804102,
      "time": 1.9215
    },
    {
      "db": 78.025808,
      "time": 1.9295
    },
    {
      "db": 78.039885,
      "time": 1.9375
    },
    {
      "db": 77.897184,
      "time": 1.9455
    },
    {
      "db": 77.415239,
      "time": 1.9535
    },
    {
      "db": 76.177836,
      "time": 1.9615
    },
    {
      "db": 73.622595,
      "time": 1.9695
    },
    {
      "db": 69.232982,
      "time": 1.9775
    },
    {
      "db": 63.956055,
      "time": 1.9855
    },
    {
      "db": 60.070551,
      "time": 1.9935
    },
    {
      "db": 55.650373,
      "time": 2.0015
    },
    {
      "db": 49.167557,
      "time": 2.0095
    },
    {
      "db": 40.942418,
      "time": 2.0175
    },
    {
      "db": 35.949308,
      "time": 2.0255
    },
    {
      "db": 43.195301,
      "time": 2.0335
    },
    {
      "db": 50.994294,
      "time": 2.0415
    },
    {
      "db": 56.550892,
      "time": 2.0495
    },
    {
      "db": 60.423072,
      "time": 2.0575
    },
    {
      "db": 63.70331,
      "time": 2.0655
    },
    {
      "db": 65.89113,
      "time": 2.0735
    },
    {
      "db": 65.905812,
      "time": 2.0815
    },
    {
      "db": 64.673607,
      "time": 2.0895
    },
    {
      "db": 64.754435,
      "time": 2.0975
    },
    {
      "db": 65.634482,
      "time": 2.1055
    },
    {
      "db": 64.872922,
      "time": 2.1135
    },
    {
      "db": 62.803705,
      "time": 2.1215
    },
    {
      "db": 59.783012,
      "time": 2.1295
    },
    {
      "db": 54.770045,
      "time": 2.1375
    },
    {
      "db": 47.321941,
      "time": 2.1455
    },
    {
      "db": 44.756268,
      "time": 2.1535
    },
    {
      "db": 54.885241,
      "time": 2.1615
    },
    {
      "db": 61.13202,
      "time": 2.1695
    },
    {
      "db": 64.0845,
      "time": 2.1775
    },
    {
      "db": 65.67971,
      "time": 2.1855
    },
    {
      "db": 70.562689,
      "time": 2.1935
    },
    {
      "db": 75.156242,
      "time": 2.2015
    },
    {
      "db": 77.596789,
      "time": 2.2095
    },
    {
      "db": 78.484053,
      "time": 2.2175
    },
    {
      "db": 78.469344,
      "time": 2.2255
    },
    {
      "db": 78.23634,
      "time": 2.2335
    },
    {
      "db": 77.974097,
      "time": 2.2415
    },
    {
      "db": 77.670443,
      "time": 2.2495
    },
    {
      "db": 77.338292,
      "time": 2.2575
    },
    {
      "db": 77.065059,
      "time": 2.2655
    },
    {
      "db": 77.045307,
      "time": 2.2735
    },
    {
      "db": 77.539612,
      "time": 2.2815
    },
    {
      "db": 78.402445,
      "time": 2.2895
    },
    {
      "db": 78.725128,
      "time": 2.2975
    },
    {
      "db": 77.933771,
      "time": 2.3055
    },
    {
      "db": 76.745964,
      "time": 2.3135
    },
    {
      "db": 76.278399,
      "time": 2.3215
    },
    {
      "db": 76.235083,
      "time": 2.3295
    },
    {
      "db": 76.203292,
      "time": 2.3375
    },
    {
      "db": 76.062026,
      "time": 2.3455
    },
    {
      "db": 75.855007,
      "time": 2.3535
    },
    {
      "db": 75.763266,
      "time": 2.3615
    },
    {
      "db": 75.77688,
      "time": 2.3695
    },
    {
      "db": 75.794502,
      "time": 2.3775
    },
    {
      "db": 75.858665,
      "time": 2.3855
    },
    {
      "db": 75.91707,
      "time": 2.3935
    },
    {
      "db": 75.943582,
      "time": 2.4015
    },
    {
      "db": 76.048732,
      "time": 2.4095
    },
    {
      "db": 76.072882,
      "time": 2.4175
    },
    {
      "db": 75.673065,
      "time": 2.4255
    },
    {
      "db": 74.914716,
      "time": 2.4335
    },
    {
      "db": 73.937317,
      "time": 2.4415
    },
    {
      "db": 72.67598,
      "time": 2.4495
    },
    {
      "db": 71.157722,
      "time": 2.4575
    },
    {
      "db": 69.492485,
      "time": 2.4655
    },
    {
      "db": 67.681474,
      "time": 2.4735
    },
    {
      "db": 65.72741,
      "time": 2.4815
    },
    {
      "db": 65.194072,
      "time": 2.4895
    },
    {
      "db": 65.828217,
      "time": 2.4975
    },
    {
      "db": 65.615063,
      "time": 2.5055
    },
    {
      "db": 67.260667,
      "time": 2.5135
    },
    {
      "db": 68.577536,
      "time": 2.5215
    },
    {
      "db": 67.575533,
      "time": 2.5295
    },
    {
      "db": 65.447258,
      "time": 2.5375
    },
    {
      "db": 63.011258,
      "time": 2.5455
    },
    {
      "db": 60.903686,
      "time": 2.5535
    },
    {
      "db": 58.311153,
      "time": 2.5615
    },
    {
      "db": 56.964713,
      "time": 2.5695
    },
    {
      "db": 60.322041,
      "time": 2.5775
    },
    {
      "db": 60.6525,
      "time": 2.5855
    },
    {
      "db": 56.430332,
      "time": 2.5935
    },
    {
      "db": 48.690813,
      "time": 2.6015
    },
    {
      "db": 42.890418,
      "time": 2.6095
    },
    {
      "db": 45.287316,
      "time": 2.6175
    },
    {
      "db": 54.881593,
      "time": 2.6255
    },
    {
      "db": 63.093551,
      "time": 2.6335
    },
    {
      "db": 67.795095,
      "time": 2.6415
    },
    {
      "db": 69.367137,
      "time": 2.6495
    },
    {
      "db": 68.332323,
      "time": 2.6575
    },
    {
      "db": 65.119378,
      "time": 2.6655
    },
    {
      "db": 59.799012,
      "time": 2.6735
    },
    {
      "db": 52.297948,
      "time": 2.6815
    },
    {
      "db": 45.099138,
      "time": 2.6895
    },
    {
      "db": 41.835909,
      "time": 2.6975
    },
    {
      "db": 44.071111,
      "time": 2.7055
    },
    {
      "db": 50.113816,
      "time": 2.7135
    },
    {
      "db": 56.047221,
      "time": 2.7215
    },
    {
      "db": 60.071181,
      "time": 2.7295
    },
    {
      "db": 62.045538,
      "time": 2.7375
    },
    {
      "db": 62.519154,
      "time": 2.7455
    },
    {
      "db": 63.412911,
      "time": 2.7535
    },
    {
      "db": 64.09667,
      "time": 2.7615
    },
    {
      "db": 63.381308,
      "time": 2.7695
    },
    {
      "db": 61.261795,
      "time": 2.7775
    },
    {
      "db": 59.211157,
      "time": 2.7855
    },
    {
      "db": 67.021878,
      "time": 2.7935
    },
    {
      "db": 73.601198,
      "time": 2.8015
    },
    {
      "db": 77.018186,
      "time": 2.8095
    },
    {
      "db": 78.37691,
      "time": 2.8175
    },
    {
      "db": 78.406341,
      "time": 2.8255
    },
    {
      "db": 78.16544,
      "time": 2.8335
    },
    {
      "db": 78.390627,
      "time": 2.8415
    },
    {
      "db": 78.652329,
      "time": 2.8495
    },
    {
      "db": 78.638664,
      "time": 2.8575
    },
    {
      "db": 78.36697,
      "time": 2.8655
    },
    {
      "db": 77.543192,
      "time": 2.8735
    },
    {
      "db": 75.408847,
      "time": 2.8815
    },
    {
      "db": 71.614213,
      "time": 2.8895
    },
    {
      "db": 68.21458,
      "time": 2.8975
    },
    {
      "db": 67.638388,
      "time": 2.9055
    },
    {
      "db": 69.559441,
      "time": 2.9135
    },
    {
      "db": 72.21639,
      "time": 2.9215
    },
    {
      "db": 73.824383,
      "time": 2.9295
    },
    {
      "db": 74.642501,
      "time": 2.9375
    },
    {
      "db": 75.078909,
      "time": 2.9455
    },
    {
      "db": 75.230785,
      "time": 2.9535
    },
    {
      "db": 75.183044,
      "time": 2.9615
    },
    {
      "db": 74.98959,
      "time": 2.9695
    },
    {
      "db": 74.774877,
      "time": 2.9775
    },
    {
      "db": 74.602336,
      "time": 2.9855
    },
    {
      "db": 74.416182,
      "time": 2.9935
    },
    {
      "db": 74.196485,
      "time": 3.0015
    },
    {
      "db": 74.014415,
      "time": 3.0095
    },
    {
      "db": 73.920123,
      "time": 3.0175
    },
    {
      "db": 73.851003,
      "time": 3.0255
    },
    {
      "db": 73.688805,
      "time": 3.0335
    },
    {
      "db": 73.388935,
      "time": 3.0415
    },
    {
      "db": 73.022802,
      "time": 3.0495
    },
    {
      "db": 72.602417,
      "time": 3.0575
    },
    {
      "db": 72.091264,
      "time": 3.0655
    },
    {
      "db": 71.483976,
      "time": 3.0735
    },
    {
      "db": 70.947745,
      "time": 3.0815
    },
    {
      "db": 70.655631,
      "time": 3.0895
    },
    {
      "db": 70.456821,
      "time": 3.0975
    },
    {
      "db": 70.185891,
      "time": 3.1055
    },
    {
      "db": 69.573256,
      "time": 3.1135
    },
    {
      "db": 68.147285,
      "time": 3.1215
    },
    {
      "db": 65.627759,
      "time": 3.1295
    },
    {
      "db": 62.328009,
      "time": 3.1375
    },
    {
      "db": 58.61226,
      "time": 3.1455
    },
    {
      "db": 54.583131,
      "time": 3.1535
    },
    {
      "db": 50.504681,
      "time": 3.1615
    },
    {
      "db": 48.012908,
      "time": 3.1695
    },
    {
      "db": 46.241685,
      "time": 3.1775
    },
    {
      "db": 43.900762,
      "time": 3.1855
    },
    {
      "db": 41.970184,
      "time": 3.1935
    },
    {
      "db": 40.342044,
      "time": 3.2015
    },
    {
      "db": 37.780681,
      "time": 3.2095
    },
    {
      "db": 35.72721,
      "time": 3.2175
    },
    {
      "db": 36.113784,
      "time": 3.2255
    },
    {
      "db": 36.716598,
      "time": 3.2335
    },
    {
      "db": 36.74836,
      "time": 3.2415
    },
    {
      "db": 37.508508,
      "time": 3.2495
    },
    {
      "db": 38.313595,
      "time": 3.2575
    },
    {
      "db": 38.084457,
      "time": 3.2655
    },
    {
      "db": 37.339277,
      "time": 3.2735
    },
    {
      "db": 37.597381,
      "time": 3.2815
    },
    {
      "db": 38.170422,
      "time": 3.2895
    },
    {
      "db": 36.956393,
      "time": 3.2975
    },
    {
      "db": 35.308793,
      "time": 3.3055
    },
    {
      "db": 34.70311,
      "time": 3.3135
    },
    {
      "db": 33.41863,
      "time": 3.3215
    }
  ],
  "measure": "intensity",
  "params": {
    "pitch_floor_hz": 100.0,
    "subtract_mean": true,
    "time_step": null
  },
  "parselmouth_version": "0.4.7",
  "praat_version": "6.1.38",
  "praat_version_date": "2 January 2021"
}
